{"id":1025,"collectionId":1006,"series":1101,"chapterId":1103,"luaPath":"Actor/Quest/MQ1025","suggestTrackMainQuestList":[],"rewardIdList":[101025],"activeMode":"PLAY_MODE_SINGLE","titleTextMapHash":2849435409,"descTextMapHash":1908491559,"subQuests":[{"subId":102501,"mainId":1025,"order":1,"isMpBlock":true,"showType":"QUEST_HIDDEN","isRewind":true,"trialAvatarList":[],"acceptCond":[{"type":"QUEST_COND_STATE_EQUAL","param":[102405,3,0,0,0]}],"finishCond":[{"type":"QUEST_CONTENT_ENTER_MY_WORLD","param":[3,0]}],"failCond":[],"beginExec":[],"finishExec":[],"failExec":[],"guide":{"type":"QUEST_GUIDE_NONE","param":[]},"exclusiveNpcList":[1016,10211,1015,10204,2093,10284,10285,10286,2025],"sharedNpcList":[],"exclusivePlaceList":[],"descTextMapHash":2764034014,"stepDescTextMapHash":3503768317,"guideTipsTextMapHash":3127620194},{"subId":102502,"mainId":1025,"order":5,"isMpBlock":true,"showType":"QUEST_HIDDEN","isRewind":true,"trialAvatarList":[],"acceptCond":[{"type":"QUEST_COND_STATE_EQUAL","param":[102521,3,0,0,0]}],"finishCond":[{"type":"QUEST_CONTENT_COMPLETE_TALK","param":[102502,0]}],"failCond":[],"beginExec":[],"finishExec":[],"failExec":[],"guide":{"type":"QUEST_GUIDE_NPC","param":["10200"],"guideScene":1033,"guideStyle":"QUEST_GUIDE_STYLE_TARGET","guideLayer":"QUEST_GUIDE_LAYER_SCENE"},"exclusiveNpcList":[10200,1017,2144,2067,2145,2084],"sharedNpcList":[],"exclusivePlaceList":[],"descTextMapHash":908060102,"stepDescTextMapHash":1574858533,"guideTipsTextMapHash":381043210},{"subId":102503,"mainId":1025,"order":7,"subIdSet":1,"isMpBlock":true,"isRewind":true,"trialAvatarList":[],"acceptCond":[{"type":"QUEST_COND_STATE_EQUAL","param":[102517,3,0,0,0]}],"finishCond":[{"type":"QUEST_CONTENT_COMPLETE_TALK","param":[102503,0]}],"failCond":[],"beginExec":[],"finishExec":[{"type":"QUEST_EXEC_ADD_QUEST_PROGRESS","param":["10251101","1"]}],"failExec":[],"guide":{"type":"QUEST_GUIDE_NPC","param":["205501"],"guideScene":3,"guideStyle":"QUEST_GUIDE_STYLE_TARGET","guideLayer":"QUEST_GUIDE_LAYER_SCENE"},"exclusiveNpcList":[2055,2038],"sharedNpcList":[],"exclusivePlaceList":[],"descTextMapHash":702010158,"stepDescTextMapHash":559344765,"guideTipsTextMapHash":3293113010},{"subId":102504,"mainId":1025,"order":8,"subIdSet":1,"isMpBlock":true,"isRewind":true,"trialAvatarList":[],"acceptCond":[{"type":"QUEST_COND_STATE_EQUAL","param":[102517,3,0,0,0]}],"finishCond":[{"type":"QUEST_CONTENT_COMPLETE_TALK","param":[102504,0]}],"failCond":[],"beginExec":[],"finishExec":[{"type":"QUEST_EXEC_ADD_QUEST_PROGRESS","param":["10251101","1"]}],"failExec":[],"guide":{"type":"QUEST_GUIDE_NPC","param":["203401"],"guideScene":3,"guideStyle":"QUEST_GUIDE_STYLE_TARGET","guideLayer":"QUEST_GUIDE_LAYER_SCENE"},"exclusiveNpcList":[2034,2035],"sharedNpcList":[],"exclusivePlaceList":[],"descTextMapHash":4227877614,"stepDescTextMapHash":2276127773,"guideTipsTextMapHash":2947324258},{"subId":102505,"mainId":1025,"order":11,"isRewind":true,"trialAvatarList":[],"acceptCond":[{"type":"QUEST_COND_STATE_EQUAL","param":[102512,3,0,0,0]}],"finishCond":[{"type":"QUEST_CONTENT_COMPLETE_TALK","param":[102505,0]}],"failCond":[],"beginExec":[{"type":"QUEST_EXEC_REFRESH_GROUP_SUITE","param":["3","133107106,2"]}],"finishExec":[],"failExec":[],"guide":{"type":"QUEST_GUIDE_NPC","param":["207101"],"guideScene":3,"guideStyle":"QUEST_GUIDE_STYLE_TARGET","guideLayer":"QUEST_GUIDE_LAYER_SCENE"},"exclusiveNpcList":[2071],"sharedNpcList":[],"exclusivePlaceList":[],"descTextMapHash":3711576166,"stepDescTextMapHash":775677773,"guideTipsTextMapHash":373315402},{"subId":102506,"mainId":1025,"order":12,"isRewind":true,"trialAvatarList":[],"acceptCond":[{"type":"QUEST_COND_STATE_EQUAL","param":[102505,3,0,0,0]}],"finishCond":[{"type":"QUEST_CONTENT_COMPLETE_TALK","param":[102506,0]}],"failCond":[],"beginExec":[],"finishExec":[{"type":"QUEST_EXEC_SET_QUEST_GLOBAL_VAR","param":["10007","1"]}],"failExec":[],"guide":{"type":"QUEST_GUIDE_LOCATION","param":["Q102506Trigger","15"],"guideScene":3,"guideStyle":"QUEST_GUIDE_STYLE_TARGET","guideLayer":"QUEST_GUIDE_LAYER_SCENE"},"exclusiveNpcList":[1016,10211,1015,10232,2093,2083,2054],"sharedNpcList":[],"exclusivePlaceList":[],"descTextMapHash":1148236926,"stepDescTextMapHash":2636346245,"guideTipsTextMapHash":1876053802},{"subId":102507,"mainId":1025,"order":13,"isMpBlock":true,"showType":"QUEST_HIDDEN","isRewind":true,"trialAvatarList":[],"acceptCond":[{"type":"QUEST_COND_STATE_EQUAL","param":[102506,3,0,0,0]}],"finishCond":[{"type":"QUEST_CONTENT_COMPLETE_TALK","param":[102507,0]}],"failCond":[],"beginExec":[],"finishExec":[{"type":"QUEST_EXEC_ADD_QUEST_PROGRESS","param":["10251301","1"]}],"failExec":[],"guide":{"type":"QUEST_GUIDE_NONE","param":[]},"exclusiveNpcList":[],"sharedNpcList":[],"exclusivePlaceList":[],"descTextMapHash":2407962542,"stepDescTextMapHash":860634109,"guideTipsTextMapHash":4017006450},{"subId":102508,"mainId":1025,"order":14,"isMpBlock":true,"showType":"QUEST_HIDDEN","isRewind":true,"trialAvatarList":[],"acceptCond":[{"type":"QUEST_COND_STATE_EQUAL","param":[102506,3,0,0,0]}],"finishCond":[{"type":"QUEST_CONTENT_COMPLETE_TALK","param":[102508,0]}],"failCond":[],"beginExec":[],"finishExec":[{"type":"QUEST_EXEC_ADD_QUEST_PROGRESS","param":["10251301","1"]}],"failExec":[],"guide":{"type":"QUEST_GUIDE_NONE","param":[]},"exclusiveNpcList":[],"sharedNpcList":[],"exclusivePlaceList":[],"descTextMapHash":4037916470,"stepDescTextMapHash":3784887829,"guideTipsTextMapHash":1341049762},{"subId":102509,"mainId":1025,"order":15,"isMpBlock":true,"showType":"QUEST_HIDDEN","isRewind":true,"trialAvatarList":[],"acceptCond":[{"type":"QUEST_COND_STATE_EQUAL","param":[102506,3,0,0,0]}],"finishCond":[{"type":"QUEST_CONTENT_COMPLETE_TALK","param":[102509,0]}],"failCond":[],"beginExec":[],"finishExec":[{"type":"QUEST_EXEC_ADD_QUEST_PROGRESS","param":["10251301","1"]}],"failExec":[],"guide":{"type":"QUEST_GUIDE_NONE","param":[]},"exclusiveNpcList":[],"sharedNpcList":[],"exclusivePlaceList":[],"descTextMapHash":1921759582,"stepDescTextMapHash":42590605,"guideTipsTextMapHash":2288934698},{"subId":102510,"mainId":1025,"order":21,"finishParent":true,"isRewind":true,"trialAvatarList":[],"acceptCond":[{"type":"QUEST_COND_STATE_EQUAL","param":[102514,3,0,0,0]}],"finishCond":[{"type":"QUEST_CONTENT_COMPLETE_TALK","param":[102510,0]}],"failCond":[],"beginExec":[],"finishExec":[{"type":"QUEST_EXEC_SET_QUEST_GLOBAL_VAR","param":["10006","1"]}],"failExec":[],"guide":{"type":"QUEST_GUIDE_NPC","param":["10232"],"guideScene":3,"guideStyle":"QUEST_GUIDE_STYLE_TARGET","guideLayer":"QUEST_GUIDE_LAYER_SCENE"},"exclusiveNpcList":[10232],"sharedNpcList":[],"exclusivePlaceList":[],"descTextMapHash":2815222158,"stepDescTextMapHash":2189920237,"guideTipsTextMapHash":3890638466},{"subId":102511,"mainId":1025,"order":9,"isMpBlock":true,"showType":"QUEST_HIDDEN","isRewind":true,"trialAvatarList":[],"acceptCond":[{"type":"QUEST_COND_STATE_EQUAL","param":[102517,3,0,0,0]}],"finishCond":[{"type":"QUEST_CONTENT_ADD_QUEST_PROGRESS","param":[10251101,0],"count":2}],"failCond":[],"beginExec":[],"finishExec":[{"type":"QUEST_EXEC_ADD_QUEST_PROGRESS","param":["10251201","1"]}],"failExec":[],"guide":{"type":"QUEST_GUIDE_NONE","param":[]},"exclusiveNpcList":[],"sharedNpcList":[],"exclusivePlaceList":[],"descTextMapHash":3218947758,"stepDescTextMapHash":2618259317,"guideTipsTextMapHash":857278850},{"subId":102512,"mainId":1025,"order":10,"isMpBlock":true,"showType":"QUEST_HIDDEN","isRewind":true,"trialAvatarList":[],"acceptCond":[{"type":"QUEST_COND_STATE_EQUAL","param":[102517,3,0,0,0]}],"finishCond":[{"type":"QUEST_CONTENT_ADD_QUEST_PROGRESS","param":[10251201,0],"count":1}],"failCond":[],"beginExec":[],"finishExec":[],"failExec":[],"guide":{"type":"QUEST_GUIDE_NONE","param":[]},"exclusiveNpcList":[],"sharedNpcList":[],"exclusivePlaceList":[],"descTextMapHash":1545146038,"stepDescTextMapHash":2955331637,"guideTipsTextMapHash":2544217946},{"subId":102513,"mainId":1025,"order":19,"subIdSet":2,"isMpBlock":true,"isRewind":true,"trialAvatarList":[],"acceptCond":[{"type":"QUEST_COND_STATE_EQUAL","param":[102506,3,0,0,0]}],"finishCond":[{"type":"QUEST_CONTENT_ADD_QUEST_PROGRESS","param":[10251301,0],"count":3}],"failCond":[],"beginExec":[],"finishExec":[{"type":"QUEST_EXEC_ADD_QUEST_PROGRESS","param":["10251401","1"]}],"failExec":[],"guide":{"type":"QUEST_GUIDE_LOCATION","param":["Q102506Trigger","15"],"guideScene":3,"guideStyle":"QUEST_GUIDE_STYLE_TARGET","guideLayer":"QUEST_GUIDE_LAYER_SCENE"},"exclusiveNpcList":[1016,10211,1015,10232,2093,2083,2054],"sharedNpcList":[],"exclusivePlaceList":[],"descTextMapHash":461056158,"stepDescTextMapHash":659287565,"guideTipsTextMapHash":960177882},{"subId":102514,"mainId":1025,"order":20,"isMpBlock":true,"showType":"QUEST_HIDDEN","isRewind":true,"trialAvatarList":[],"acceptCond":[{"type":"QUEST_COND_STATE_EQUAL","param":[102506,3,0,0,0]}],"finishCond":[{"type":"QUEST_CONTENT_ADD_QUEST_PROGRESS","param":[10251401,0],"count":1}],"failCond":[],"beginExec":[],"finishExec":[],"failExec":[],"guide":{"type":"QUEST_GUIDE_NONE","param":[]},"exclusiveNpcList":[],"sharedNpcList":[],"exclusivePlaceList":[],"descTextMapHash":3891216502,"stepDescTextMapHash":254303893,"guideTipsTextMapHash":3536090394},{"subId":102515,"mainId":1025,"order":3,"isRewind":true,"trialAvatarList":[],"acceptCond":[{"type":"QUEST_COND_STATE_EQUAL","param":[102516,3,0,0,0]}],"finishCond":[{"type":"QUEST_CONTENT_COMPLETE_TALK","param":[102515,0]}],"failCond":[],"beginExec":[{"type":"QUEST_EXEC_UNLOCK_POINT","param":["3","218"]}],"finishExec":[],"failExec":[],"guide":{"type":"QUEST_GUIDE_NPC","param":["208401"],"guideScene":3,"guideStyle":"QUEST_GUIDE_STYLE_TARGET","guideLayer":"QUEST_GUIDE_LAYER_SCENE"},"exclusiveNpcList":[2084],"sharedNpcList":[],"exclusivePlaceList":[],"descTextMapHash":3832539726,"stepDescTextMapHash":2552964981,"guideTipsTextMapHash":1230191242},{"subId":102516,"mainId":1025,"order":2,"isMpBlock":true,"showType":"QUEST_HIDDEN","isRewind":true,"trialAvatarList":[],"acceptCond":[{"type":"QUEST_COND_STATE_EQUAL","param":[102501,3,0,0,0]}],"finishCond":[{"type":"QUEST_CONTENT_COMPLETE_TALK","param":[102516,0]}],"failCond":[],"beginExec":[],"finishExec":[],"failExec":[],"guide":{"type":"QUEST_GUIDE_NONE","param":[]},"exclusiveNpcList":[1016,10211,1015,10204,2093,10284,10285,10286,2025],"sharedNpcList":[],"exclusivePlaceList":[],"descTextMapHash":1905948638,"stepDescTextMapHash":3043202117,"guideTipsTextMapHash":1670148730},{"subId":102517,"mainId":1025,"order":6,"isRewind":true,"trialAvatarList":[],"acceptCond":[{"type":"QUEST_COND_STATE_EQUAL","param":[102502,3,0,0,0]}],"finishCond":[{"type":"QUEST_CONTENT_ENTER_MY_WORLD","param":[3,0]}],"failCond":[],"beginExec":[],"finishExec":[{"type":"QUEST_EXEC_DEL_PACK_ITEM","param":["100606","1"]}],"failExec":[],"guide":{"type":"QUEST_GUIDE_LOCATION","param":["Q102503DJ"],"guideScene":3,"guideStyle":"QUEST_GUIDE_STYLE_TARGET","guideLayer":"QUEST_GUIDE_LAYER_SCENE"},"exclusiveNpcList":[2144,2067,2145],"sharedNpcList":[],"exclusivePlaceList":[],"descTextMapHash":3898841334,"stepDescTextMapHash":2290184685,"guideTipsTextMapHash":4262289850},{"subId":102518,"mainId":1025,"order":16,"isMpBlock":true,"showType":"QUEST_HIDDEN","isRewind":true,"trialAvatarList":[],"acceptCond":[{"type":"QUEST_COND_STATE_EQUAL","param":[102506,3,0,0,0]}],"finishCond":[{"type":"QUEST_CONTENT_COMPLETE_TALK","param":[102518,0]}],"failCond":[],"beginExec":[],"finishExec":[{"type":"QUEST_EXEC_ADD_QUEST_PROGRESS","param":["10251301","1"]}],"failExec":[],"guide":{"type":"QUEST_GUIDE_NONE","param":[]},"exclusiveNpcList":[],"sharedNpcList":[],"exclusivePlaceList":[],"descTextMapHash":1866638590,"stepDescTextMapHash":3258777237,"guideTipsTextMapHash":1118212330},{"subId":102519,"mainId":1025,"order":17,"isMpBlock":true,"showType":"QUEST_HIDDEN","isRewind":true,"trialAvatarList":[],"acceptCond":[{"type":"QUEST_COND_STATE_EQUAL","param":[102506,3,0,0,0]}],"finishCond":[{"type":"QUEST_CONTENT_COMPLETE_TALK","param":[102519,0]}],"failCond":[],"beginExec":[],"finishExec":[{"type":"QUEST_EXEC_ADD_QUEST_PROGRESS","param":["10251301","1"]}],"failExec":[],"guide":{"type":"QUEST_GUIDE_NONE","param":[]},"exclusiveNpcList":[],"sharedNpcList":[],"exclusivePlaceList":[],"descTextMapHash":2201692230,"stepDescTextMapHash":2728283013,"guideTipsTextMapHash":1451055354},{"subId":102520,"mainId":1025,"order":18,"isMpBlock":true,"showType":"QUEST_HIDDEN","isRewind":true,"trialAvatarList":[],"acceptCond":[{"type":"QUEST_COND_STATE_EQUAL","param":[102506,3,0,0,0]}],"finishCond":[{"type":"QUEST_CONTENT_COMPLETE_TALK","param":[102521,0]}],"failCond":[],"beginExec":[],"finishExec":[{"type":"QUEST_EXEC_ADD_QUEST_PROGRESS","param":["10251301","1"]}],"failExec":[],"guide":{"type":"QUEST_GUIDE_NONE","param":[]},"exclusiveNpcList":[],"sharedNpcList":[],"exclusivePlaceList":[],"descTextMapHash":1324536198,"stepDescTextMapHash":3144913957,"guideTipsTextMapHash":2246003162},{"subId":102521,"mainId":1025,"order":4,"isRewind":true,"trialAvatarList":[],"acceptCond":[{"type":"QUEST_COND_STATE_EQUAL","param":[102515,3,0,0,0]}],"finishCond":[{"type":"QUEST_CONTENT_ENTER_ROOM","param":[1033,0]}],"failCond":[],"beginExec":[],"finishExec":[],"failExec":[],"guide":{"type":"QUEST_GUIDE_LOCATION","param":["Q102502Paimon"],"guideScene":1033,"guideStyle":"QUEST_GUIDE_STYLE_TARGET","guideLayer":"QUEST_GUIDE_LAYER_SCENE"},"exclusiveNpcList":[2144,2067,2145,2084],"sharedNpcList":[],"exclusivePlaceList":[],"descTextMapHash":1840549054,"stepDescTextMapHash":1649790381,"guideTipsTextMapHash":2636764282}],"talks":[{"id":102502,"beginWay":"TALK_BEGIN_AUTO","beginCond":[{"type":"QUEST_COND_STATE_EQUAL","params":["102502","2"]}],"priority":5,"initDialog":10250201,"npcIds":[1005],"performCfg":"QuestDialogue/AQ/Liyue3_1025/Q102502","prePerformCfg":"","questId":1025,"assetIndex":1019593564914},{"id":102503,"beginWay":"TALK_BEGIN_AUTO","beginCond":[{"type":"QUEST_COND_STATE_EQUAL","params":["102503","2"]}],"priority":5,"initDialog":10250301,"npcIds":[205501],"performCfg":"QuestDialogue/AQ/Liyue3_1025/Q102503","prePerformCfg":"","questId":1025,"assetIndex":254530627262},{"id":102504,"beginWay":"TALK_BEGIN_AUTO","beginCond":[{"type":"QUEST_COND_STATE_EQUAL","params":["102504","2"]}],"priority":5,"initDialog":10250401,"npcIds":[203401],"performCfg":"QuestDialogue/AQ/Liyue3_1025/Q102504","prePerformCfg":"","questId":1025,"assetIndex":487720580905},{"id":102505,"beginWay":"TALK_BEGIN_AUTO","beginCond":[{"type":"QUEST_COND_STATE_EQUAL","params":["102505","2"]}],"priority":5,"initDialog":10250501,"npcIds":[207101],"performCfg":"QuestDialogue/AQ/Liyue3_1025/Q102505","prePerformCfg":"","questId":1025,"assetIndex":370757097331},{"id":102506,"beginWay":"TALK_BEGIN_AUTO","beginCond":[{"type":"QUEST_COND_STATE_EQUAL","params":["102506","2"]}],"priority":5,"initDialog":10250601,"npcIds":[208301],"performCfg":"QuestDialogue/AQ/Liyue3_1025/Q102506","prePerformCfg":"","questId":1025,"assetIndex":271856455904},{"id":102507,"beginWay":"TALK_BEGIN_MANUAL","beginCond":[{"type":"QUEST_COND_STATE_EQUAL","params":["102507","2"]}],"priority":5,"initDialog":10250701,"npcIds":[209301],"performCfg":"","prePerformCfg":"","questId":1025,"assetIndex":914301217394},{"id":102508,"beginWay":"TALK_BEGIN_MANUAL","beginCond":[{"type":"QUEST_COND_STATE_EQUAL","params":["102508","2"]}],"priority":5,"initDialog":10250801,"npcIds":[208301],"performCfg":"","prePerformCfg":"","questId":1025,"assetIndex":706017034243},{"id":102509,"beginWay":"TALK_BEGIN_MANUAL","beginCond":[{"type":"QUEST_COND_STATE_EQUAL","params":["102509","2"]}],"priority":5,"initDialog":10250901,"npcIds":[205401],"performCfg":"","prePerformCfg":"","questId":1025,"assetIndex":61845052460},{"id":102510,"beginWay":"TALK_BEGIN_MANUAL","beginCond":[{"type":"QUEST_COND_STATE_EQUAL","params":["102510","2"]}],"priority":5,"initDialog":10251001,"npcIds":[10232],"performCfg":"QuestDialogue/AQ/Liyue3_1025/Q102510","prePerformCfg":"","questId":1025,"assetIndex":234236112806},{"id":102515,"beginWay":"TALK_BEGIN_MANUAL","beginCond":[{"type":"QUEST_COND_STATE_EQUAL","params":["102515","2"]}],"priority":5,"initDialog":10251501,"npcIds":[208401],"performCfg":"QuestDialogue/AQ/Liyue3_1025/Q102515","prePerformCfg":"","questId":1025,"assetIndex":743733224681},{"id":102516,"beginWay":"TALK_BEGIN_AUTO","beginCond":[{"type":"QUEST_COND_STATE_EQUAL","params":["102516","2"]}],"priority":5,"initDialog":10250101,"npcIds":[1005],"performCfg":"QuestDialogue/AQ/Liyue3_1025/Q102516","prePerformCfg":"","questId":1025,"assetIndex":618189264074},{"id":102518,"beginWay":"TALK_BEGIN_MANUAL","beginCond":[{"type":"QUEST_COND_STATE_EQUAL","params":["102513","2"]}],"heroTalk":"TALK_HERO_MAIN","priority":5,"initDialog":10251801,"npcIds":[10211],"performCfg":"","prePerformCfg":"","questId":1025,"assetIndex":346178675977},{"id":102519,"beginWay":"TALK_BEGIN_MANUAL","beginCond":[{"type":"QUEST_COND_STATE_EQUAL","params":["102513","2"]}],"heroTalk":"TALK_HERO_MAIN","priority":5,"initDialog":10251901,"npcIds":[1016],"performCfg":"","prePerformCfg":"","questId":1025,"assetIndex":954296668332},{"id":102521,"beginWay":"TALK_BEGIN_MANUAL","beginCond":[{"type":"QUEST_COND_STATE_EQUAL","params":["102513","2"]}],"heroTalk":"TALK_HERO_MAIN","priority":5,"initDialog":10252101,"npcIds":[1015],"performCfg":"","prePerformCfg":"","questId":1025,"assetIndex":980957788147},{"id":102525,"beginWay":"TALK_BEGIN_MANUAL","beginCond":[{"type":"QUEST_COND_STATE_EQUAL","params":["102513","2"]}],"priority":5,"initDialog":10252501,"npcIds":[2003008],"performCfg":"","prePerformCfg":"","questId":1025,"assetIndex":478259273607},{"id":102526,"beginWay":"TALK_BEGIN_MANUAL","beginCond":[{"type":"QUEST_COND_STATE_EQUAL","params":["102513","2"]}],"priority":5,"initDialog":10252601,"npcIds":[2003009],"performCfg":"","prePerformCfg":"","questId":1025,"assetIndex":511074050015},{"id":102527,"beginWay":"TALK_BEGIN_MANUAL","beginCond":[{"type":"QUEST_COND_STATE_EQUAL","params":["102513","2"]}],"priority":5,"initDialog":10252701,"npcIds":[2003010],"performCfg":"","prePerformCfg":"","questId":1025,"assetIndex":416967809847},{"id":102528,"beginWay":"TALK_BEGIN_MANUAL","beginCond":[{"type":"QUEST_COND_STATE_EQUAL","params":["102513","2"]}],"priority":5,"initDialog":10252801,"npcIds":[2003011],"performCfg":"","prePerformCfg":"","questId":1025,"assetIndex":590815864288},{"id":102529,"beginWay":"TALK_BEGIN_MANUAL","beginCond":[{"type":"QUEST_COND_STATE_EQUAL","params":["102513","2"]}],"priority":5,"initDialog":10252901,"npcIds":[2003012],"performCfg":"","prePerformCfg":"","questId":1025,"assetIndex":30182875917},{"id":102530,"beginWay":"TALK_BEGIN_MANUAL","beginCond":[{"type":"QUEST_COND_STATE_EQUAL","params":["102513","2"]}],"priority":5,"initDialog":10253001,"npcIds":[10319],"performCfg":"","prePerformCfg":"","questId":1025,"assetIndex":283380904491},{"id":102531,"beginWay":"TALK_BEGIN_MANUAL","beginCond":[{"type":"QUEST_COND_STATE_EQUAL","params":["102513","2"]}],"priority":5,"initDialog":10253101,"npcIds":[10320],"performCfg":"","prePerformCfg":"","questId":1025,"assetIndex":316456000250},{"id":102532,"beginWay":"TALK_BEGIN_MANUAL","beginCond":[{"type":"QUEST_COND_STATE_EQUAL","params":["102513","2"]}],"priority":5,"initDialog":10253201,"npcIds":[10321],"performCfg":"","prePerformCfg":"","questId":1025,"assetIndex":230716083549},{"id":102533,"beginWay":"TALK_BEGIN_MANUAL","beginCond":[{"type":"QUEST_COND_STATE_EQUAL","params":["102513","2"]}],"heroTalk":"TALK_HERO_MAIN","priority":5,"initDialog":10253301,"npcIds":[10232],"performCfg":"","prePerformCfg":"","questId":1025,"assetIndex":628728538688},{"id":102534,"beginWay":"TALK_BEGIN_MANUAL","beginCond":[{"type":"QUEST_COND_STATE_EQUAL","params":["102517","2"]}],"heroTalk":"TALK_HERO_MAIN","priority":5,"initDialog":10253401,"npcIds":[10232],"performCfg":"QuestDialogue/AQ/Liyue3_1025/Q102534","prePerformCfg":"","questId":1025,"assetIndex":14467374386},{"id":102535,"beginWay":"TALK_BEGIN_MANUAL","beginCond":[{"type":"QUEST_COND_STATE_EQUAL","params":["102503","3"]}],"priority":5,"initDialog":10250301,"npcIds":[205501],"performCfg":"QuestDialogue/AQ/Liyue3_1025/Q102503","prePerformCfg":"","questId":1025,"assetIndex":1055161615024},{"id":102536,"beginWay":"TALK_BEGIN_MANUAL","beginCond":[{"type":"QUEST_COND_STATE_EQUAL","params":["102504","3"]}],"priority":5,"initDialog":10250401,"npcIds":[203401],"performCfg":"QuestDialogue/AQ/Liyue3_1025/Q102504","prePerformCfg":"","questId":1025,"assetIndex":574253783610},{"id":102540,"beginWay":"TALK_BEGIN_MANUAL","beginCond":[{"type":"QUEST_COND_STATE_EQUAL","params":["102515","3"]}],"priority":5,"initDialog":10254001,"npcIds":[208401],"performCfg":"","prePerformCfg":"","questId":1025,"assetIndex":942475961507},{"id":102541,"beginWay":"TALK_BEGIN_MANUAL","beginCond":[{"type":"QUEST_COND_STATE_EQUAL","params":["102510","2"]}],"heroTalk":"TALK_HERO_MAIN","priority":5,"initDialog":10251801,"npcIds":[10211],"performCfg":"","prePerformCfg":"","questId":1025,"assetIndex":474053078623},{"id":102542,"beginWay":"TALK_BEGIN_MANUAL","beginCond":[{"type":"QUEST_COND_STATE_EQUAL","params":["102510","2"]}],"heroTalk":"TALK_HERO_MAIN","priority":5,"initDialog":10251901,"npcIds":[1016],"performCfg":"","prePerformCfg":"","questId":1025,"assetIndex":165206579734},{"id":102543,"beginWay":"TALK_BEGIN_MANUAL","beginCond":[{"type":"QUEST_COND_STATE_EQUAL","params":["102510","2"]}],"heroTalk":"TALK_HERO_MAIN","priority":5,"initDialog":10252101,"npcIds":[1015],"performCfg":"","prePerformCfg":"","questId":1025,"assetIndex":565969746350},{"id":102544,"beginWay":"TALK_BEGIN_MANUAL","beginCond":[{"type":"QUEST_COND_STATE_EQUAL","params":["102510","2"]}],"priority":5,"initDialog":10252501,"npcIds":[2003008],"performCfg":"","prePerformCfg":"","questId":1025,"assetIndex":36457342021},{"id":102545,"beginWay":"TALK_BEGIN_MANUAL","beginCond":[{"type":"QUEST_COND_STATE_EQUAL","params":["102510","2"]}],"priority":5,"initDialog":10252601,"npcIds":[2003009],"performCfg":"","prePerformCfg":"","questId":1025,"assetIndex":335451020539},{"id":102546,"beginWay":"TALK_BEGIN_MANUAL","beginCond":[{"type":"QUEST_COND_STATE_EQUAL","params":["102510","2"]}],"priority":5,"initDialog":10252701,"npcIds":[2003010],"performCfg":"","prePerformCfg":"","questId":1025,"assetIndex":748403743578},{"id":102547,"beginWay":"TALK_BEGIN_MANUAL","beginCond":[{"type":"QUEST_COND_STATE_EQUAL","params":["102510","2"]}],"priority":5,"initDialog":10252801,"npcIds":[2003011],"performCfg":"","prePerformCfg":"","questId":1025,"assetIndex":194348603486},{"id":102548,"beginWay":"TALK_BEGIN_MANUAL","beginCond":[{"type":"QUEST_COND_STATE_EQUAL","params":["102510","2"]}],"priority":5,"initDialog":10252901,"npcIds":[2003012],"performCfg":"","prePerformCfg":"","questId":1025,"assetIndex":759566279913},{"id":102549,"beginWay":"TALK_BEGIN_MANUAL","beginCond":[{"type":"QUEST_COND_STATE_EQUAL","params":["102510","2"]}],"priority":5,"initDialog":10253001,"npcIds":[10319],"performCfg":"","prePerformCfg":"","questId":1025,"assetIndex":824295181209},{"id":102550,"beginWay":"TALK_BEGIN_MANUAL","beginCond":[{"type":"QUEST_COND_STATE_EQUAL","params":["102510","2"]}],"priority":5,"initDialog":10253101,"npcIds":[10320],"performCfg":"","prePerformCfg":"","questId":1025,"assetIndex":987202107247},{"id":102551,"beginWay":"TALK_BEGIN_MANUAL","beginCond":[{"type":"QUEST_COND_STATE_EQUAL","params":["102510","2"]}],"priority":5,"initDialog":10253201,"npcIds":[10321],"performCfg":"","prePerformCfg":"","questId":1025,"assetIndex":434758738699},{"id":102564,"beginWay":"TALK_BEGIN_MANUAL","beginCond":[{"type":"QUEST_COND_STATE_EQUAL","params":["102510","2"]}],"priority":5,"initDialog":10250701,"npcIds":[209301],"performCfg":"","prePerformCfg":"","questId":1025,"assetIndex":674420488652},{"id":102565,"beginWay":"TALK_BEGIN_MANUAL","beginCond":[{"type":"QUEST_COND_STATE_EQUAL","params":["102510","2"]}],"priority":5,"initDialog":10250801,"npcIds":[208301],"performCfg":"","prePerformCfg":"","questId":1025,"assetIndex":854113554374},{"id":102566,"beginWay":"TALK_BEGIN_MANUAL","beginCond":[{"type":"QUEST_COND_STATE_EQUAL","params":["102510","2"]}],"priority":5,"initDialog":10250901,"npcIds":[205401],"performCfg":"","prePerformCfg":"","questId":1025,"assetIndex":505193782523}],"preloadLuaList":[645902683150,392765187954,1021094452330],"forcePreloadLuaList":[373116172960]}