{"id":20067,"taskType":"IQ","luaPath":"Actor/Quest/IQ20067","repeatable":true,"suggestTrackMainQuestList":[],"rewardIdList":[],"activeMode":"PLAY_MODE_ALL","taskId":40031,"titleTextMapHash":2703550799,"descTextMapHash":2453374534,"subQuests":[{"subId":2006701,"mainId":20067,"order":1,"isRewind":true,"trialAvatarList":[],"acceptCond":[{"type":"QUEST_COND_DAILY_TASK_START","param":[40031,0,0,0,0]}],"finishCond":[{"type":"QUEST_CONTENT_COMPLETE_TALK","param":[2006713,0]}],"failCond":[],"beginExec":[],"finishExec":[],"failExec":[],"guide":{"type":"QUEST_GUIDE_NPC","param":["1405"],"guideScene":3,"guideStyle":"QUEST_GUIDE_STYLE_START","guideLayer":"QUEST_GUIDE_LAYER_SCENE"},"exclusiveNpcList":[1405],"exclusiveNpcPriority":1100,"sharedNpcList":[],"exclusivePlaceList":[],"descTextMapHash":1714792612,"stepDescTextMapHash":625900229,"guideTipsTextMapHash":2991291102},{"subId":2006702,"mainId":20067,"order":2,"isRewind":true,"trialAvatarList":[],"acceptCondComb":"LOGIC_AND","acceptCond":[{"type":"QUEST_COND_STATE_EQUAL","param":[2006701,3,0,0,0]},{"type":"QUEST_COND_DAILY_TASK_START","param":[40031,0,0,0,0]}],"finishCond":[{"type":"QUEST_CONTENT_LUA_NOTIFY","paramString":"1330030811","param":[0,0],"count":1}],"failCond":[],"beginExec":[{"type":"QUEST_EXEC_REGISTER_DYNAMIC_GROUP","param":["3","133003081"]}],"finishExec":[],"failExec":[],"guide":{"type":"QUEST_GUIDE_LOCATION","param":["Q2002105"],"guideScene":3,"guideStyle":"QUEST_GUIDE_STYLE_POINT","guideLayer":"QUEST_GUIDE_LAYER_SCENE"},"exclusiveNpcList":[1405],"exclusiveNpcPriority":1100,"sharedNpcList":[],"exclusivePlaceList":[],"descTextMapHash":27871748,"stepDescTextMapHash":595862525,"guideTipsTextMapHash":648607518},{"subId":2006703,"mainId":20067,"order":3,"trialAvatarList":[],"acceptCondComb":"LOGIC_AND","acceptCond":[{"type":"QUEST_COND_STATE_EQUAL","param":[2006702,3,0,0,0]},{"type":"QUEST_COND_DAILY_TASK_START","param":[40031,0,0,0,0]}],"finishCond":[{"type":"QUEST_CONTENT_LUA_NOTIFY","paramString":"1330030812","param":[0,0],"count":1}],"failCond":[{"type":"QUEST_CONTENT_LUA_NOTIFY","paramString":"1330030813","param":[0,0],"count":1}],"beginExec":[],"finishExec":[{"type":"QUEST_EXEC_UNREGISTER_DYNAMIC_GROUP","param":["133003081","0"]}],"failExec":[{"type":"QUEST_EXEC_ROLLBACK_QUEST","param":["2006702"]}],"guide":{"type":"QUEST_GUIDE_NONE","param":[]},"showGuide":"QUEST_GUIDE_ITEM_DISABLE","exclusiveNpcList":[1405],"exclusiveNpcPriority":1100,"sharedNpcList":[],"exclusivePlaceList":[],"descTextMapHash":1499694556,"stepDescTextMapHash":1182359197,"guideTipsTextMapHash":3451530670},{"subId":2006704,"mainId":20067,"order":4,"isRewind":true,"trialAvatarList":[],"acceptCondComb":"LOGIC_AND","acceptCond":[{"type":"QUEST_COND_STATE_EQUAL","param":[2006703,3,0,0,0]},{"type":"QUEST_COND_DAILY_TASK_START","param":[40031,0,0,0,0]}],"finishCond":[{"type":"QUEST_CONTENT_COMPLETE_TALK","param":[2006714,0]}],"failCond":[],"beginExec":[],"finishExec":[{"type":"QUEST_EXEC_UNREGISTER_DYNAMIC_GROUP","param":["133003081","0"]}],"failExec":[],"guide":{"type":"QUEST_GUIDE_NPC","param":["1405"],"guideScene":3,"guideStyle":"QUEST_GUIDE_STYLE_FINISH","guideLayer":"QUEST_GUIDE_LAYER_SCENE"},"exclusiveNpcList":[1405],"exclusiveNpcPriority":1100,"sharedNpcList":[],"exclusivePlaceList":[],"descTextMapHash":728255188,"stepDescTextMapHash":3959054925,"guideTipsTextMapHash":3520206062},{"subId":2006705,"mainId":20067,"order":5,"showType":"QUEST_HIDDEN","failParentShow":"QUEST_HIDDEN","finishParent":true,"trialAvatarList":[],"acceptCondComb":"LOGIC_AND","acceptCond":[{"type":"QUEST_COND_DAILY_TASK_START","param":[40031,0,0,0,0]},{"type":"QUEST_COND_STATE_EQUAL","param":[2006704,3,0,0,0]}],"finishCond":[{"type":"QUEST_CONTENT_QUEST_VAR_EQUAL","param":[1,3]}],"failCond":[],"beginExec":[],"finishExec":[{"type":"QUEST_EXEC_SET_DAILY_TASK_VAR","param":["40031","0","2"]},{"type":"QUEST_EXEC_SET_DAILY_TASK_VAR","param":["40040","0","1"]},{"type":"QUEST_EXEC_NOTIFY_DAILY_TASK","param":["40031"]}],"failExec":[],"guide":{"type":"QUEST_GUIDE_NONE","param":[]},"showGuide":"QUEST_GUIDE_ITEM_DISABLE","exclusiveNpcList":[],"sharedNpcList":[],"exclusivePlaceList":[],"descTextMapHash":3038611980,"stepDescTextMapHash":2405585109,"guideTipsTextMapHash":3188915670},{"subId":2006706,"mainId":20067,"order":6,"showType":"QUEST_HIDDEN","failParentShow":"QUEST_HIDDEN","finishParent":true,"trialAvatarList":[],"acceptCondComb":"LOGIC_AND","acceptCond":[{"type":"QUEST_COND_DAILY_TASK_START","param":[40031,0,0,0,0]},{"type":"QUEST_COND_STATE_EQUAL","param":[2006704,3,0,0,0]}],"finishCondComb":"LOGIC_OR","finishCond":[{"type":"QUEST_CONTENT_QUEST_VAR_EQUAL","param":[1,0]}],"failCond":[],"beginExec":[],"finishExec":[{"type":"QUEST_EXEC_NOTIFY_DAILY_TASK","param":["40031"]}],"failExec":[],"guide":{"type":"QUEST_GUIDE_NONE","param":[]},"showGuide":"QUEST_GUIDE_ITEM_DISABLE","exclusiveNpcList":[],"sharedNpcList":[],"exclusivePlaceList":[],"descTextMapHash":2412763788,"stepDescTextMapHash":332036373,"guideTipsTextMapHash":3783635158}],"talks":[{"id":2006701,"beginWay":"TALK_BEGIN_MANUAL","beginCond":[{"type":"QUEST_COND_STATE_EQUAL","params":["2006701","2"]}],"heroTalk":"TALK_HERO_MAIN","activeMode":"PLAY_MODE_HOST","nextTalks":[2006702,2006703,2006704],"priority":5,"initDialog":200670101,"npcIds":[1405],"performCfg":"","prePerformCfg":"","questId":20067,"finishExec":[{"type":"TALK_EXEC_SET_QUEST_VAR","param":["1","0","20067"]}],"assetIndex":242608895314},{"id":2006702,"heroTalk":"TALK_HERO_MAIN","activeMode":"PLAY_MODE_HOST","nextTalks":[2006705],"priority":5,"initDialog":200670201,"npcIds":[1405],"performCfg":"","prePerformCfg":"","questId":20067,"finishExec":[{"type":"TALK_EXEC_INC_QUEST_VAR","param":["1","1","20067"]}],"assetIndex":125012866361},{"id":2006703,"heroTalk":"TALK_HERO_MAIN","activeMode":"PLAY_MODE_HOST","nextTalks":[2006705],"priority":5,"initDialog":200670301,"npcIds":[1405],"performCfg":"","prePerformCfg":"","questId":20067,"assetIndex":683748650828},{"id":2006704,"heroTalk":"TALK_HERO_MAIN","activeMode":"PLAY_MODE_HOST","nextTalks":[2006705],"priority":5,"initDialog":200670401,"npcIds":[1405],"performCfg":"","prePerformCfg":"","questId":20067,"assetIndex":891389691126},{"id":2006705,"heroTalk":"TALK_HERO_MAIN","activeMode":"PLAY_MODE_HOST","nextTalks":[2006706,2006707,2006708],"priority":5,"initDialog":200670501,"npcIds":[1405],"performCfg":"","prePerformCfg":"","questId":20067,"assetIndex":448708059088},{"id":2006706,"heroTalk":"TALK_HERO_MAIN","activeMode":"PLAY_MODE_HOST","nextTalks":[2006709],"priority":5,"initDialog":200670601,"npcIds":[1405],"performCfg":"","prePerformCfg":"","questId":20067,"finishExec":[{"type":"TALK_EXEC_INC_QUEST_VAR","param":["1","1","20067"]}],"assetIndex":1050926852556},{"id":2006707,"heroTalk":"TALK_HERO_MAIN","activeMode":"PLAY_MODE_HOST","nextTalks":[2006709],"priority":5,"initDialog":200670701,"npcIds":[1405],"performCfg":"","prePerformCfg":"","questId":20067,"assetIndex":288881501038},{"id":2006708,"heroTalk":"TALK_HERO_MAIN","activeMode":"PLAY_MODE_HOST","nextTalks":[2006709],"priority":5,"initDialog":200670801,"npcIds":[1405],"performCfg":"","prePerformCfg":"","questId":20067,"assetIndex":432127532521},{"id":2006709,"heroTalk":"TALK_HERO_MAIN","activeMode":"PLAY_MODE_HOST","nextTalks":[2006710,2006711,2006712],"priority":5,"initDialog":200670901,"npcIds":[1405],"performCfg":"","prePerformCfg":"","questId":20067,"assetIndex":96264416909},{"id":2006710,"heroTalk":"TALK_HERO_MAIN","activeMode":"PLAY_MODE_HOST","nextTalks":[2006713],"priority":5,"initDialog":200671001,"npcIds":[1405],"performCfg":"","prePerformCfg":"","questId":20067,"finishExec":[{"type":"TALK_EXEC_INC_QUEST_VAR","param":["1","1","20067"]}],"assetIndex":67274551191},{"id":2006711,"heroTalk":"TALK_HERO_MAIN","activeMode":"PLAY_MODE_HOST","nextTalks":[2006713],"priority":5,"initDialog":200671101,"npcIds":[1405],"performCfg":"","prePerformCfg":"","questId":20067,"assetIndex":302646656191},{"id":2006712,"heroTalk":"TALK_HERO_MAIN","activeMode":"PLAY_MODE_HOST","nextTalks":[2006713],"priority":5,"initDialog":200671201,"npcIds":[1405],"performCfg":"","prePerformCfg":"","questId":20067,"assetIndex":673436095266},{"id":2006713,"heroTalk":"TALK_HERO_MAIN","activeMode":"PLAY_MODE_HOST","priority":5,"initDialog":200671301,"npcIds":[1405],"performCfg":"","prePerformCfg":"","questId":20067,"assetIndex":789404498857},{"id":2006714,"beginWay":"TALK_BEGIN_MANUAL","beginCond":[{"type":"QUEST_COND_STATE_EQUAL","params":["2006704","2"]}],"heroTalk":"TALK_HERO_MAIN","activeMode":"PLAY_MODE_HOST","priority":5,"initDialog":200671401,"npcIds":[1405],"performCfg":"","prePerformCfg":"","questId":20067,"assetIndex":81832453253}]}