{"id":22306,"taskType":"IQ","luaPath":"Actor/Quest/IQ22306","repeatable":true,"suggestTrackMainQuestList":[],"rewardIdList":[500111],"activeMode":"PLAY_MODE_ALL","taskId":25901,"titleTextMapHash":3152198577,"descTextMapHash":395925415,"subQuests":[{"subId":2230601,"mainId":22306,"order":1,"isRewind":true,"trialAvatarList":[],"acceptCond":[{"type":"QUEST_COND_DAILY_TASK_START","param":[25901,0,0,0,0]}],"finishCond":[{"type":"QUEST_CONTENT_COMPLETE_TALK","param":[2230601,0]}],"failCond":[],"beginExec":[],"finishExec":[],"failExec":[],"guide":{"type":"QUEST_GUIDE_NPC","param":["2033"],"guideScene":3,"guideStyle":"QUEST_GUIDE_STYLE_START","guideLayer":"QUEST_GUIDE_LAYER_UI"},"exclusiveNpcList":[2033,2013],"sharedNpcList":[],"exclusivePlaceList":[],"descTextMapHash":988527774,"stepDescTextMapHash":1523896987,"guideTipsTextMapHash":2978247660},{"subId":2230602,"mainId":22306,"order":2,"isRewind":true,"trialAvatarList":[],"acceptCondComb":"LOGIC_AND","acceptCond":[{"type":"QUEST_COND_DAILY_TASK_START","param":[25901,0,0,0,0]},{"type":"QUEST_COND_STATE_EQUAL","param":[2230601,3,0,0,0]}],"finishCond":[{"type":"QUEST_CONTENT_COMPLETE_TALK","param":[2230608,0]}],"failCond":[],"beginExec":[{"type":"QUEST_EXEC_ACTIVE_ITEM_GIVING","param":["2230602"]}],"finishExec":[],"failExec":[],"guide":{"type":"QUEST_GUIDE_NPC","param":["2013"],"guideScene":3,"guideStyle":"QUEST_GUIDE_STYLE_TARGET","guideLayer":"QUEST_GUIDE_LAYER_SCENE"},"exclusiveNpcList":[2033,2013],"sharedNpcList":[],"exclusivePlaceList":[],"descTextMapHash":1917740590,"stepDescTextMapHash":1624334827,"guideTipsTextMapHash":1389084772},{"subId":2230603,"mainId":22306,"order":3,"showType":"QUEST_HIDDEN","isRewind":true,"trialAvatarList":[],"acceptCondComb":"LOGIC_AND","acceptCond":[{"type":"QUEST_COND_DAILY_TASK_START","param":[25901,0,0,0,0]},{"type":"QUEST_COND_STATE_EQUAL","param":[2230601,3,0,0,0]}],"finishCond":[{"type":"QUEST_CONTENT_COMPLETE_TALK","param":[2230603,0]}],"failCond":[],"beginExec":[],"finishExec":[],"failExec":[],"guide":{"type":"QUEST_GUIDE_NONE","param":[]},"exclusiveNpcList":[],"sharedNpcList":[],"exclusivePlaceList":[],"descTextMapHash":1661907686,"stepDescTextMapHash":1479355203,"guideTipsTextMapHash":898978324},{"subId":2230604,"mainId":22306,"order":4,"showType":"QUEST_HIDDEN","isRewind":true,"trialAvatarList":[],"acceptCondComb":"LOGIC_AND","acceptCond":[{"type":"QUEST_COND_DAILY_TASK_START","param":[25901,0,0,0,0]},{"type":"QUEST_COND_STATE_EQUAL","param":[2230601,3,0,0,0]}],"finishCond":[{"type":"QUEST_CONTENT_ADD_QUEST_PROGRESS","param":[223060401,0],"count":1}],"failCond":[],"beginExec":[],"finishExec":[],"failExec":[],"guide":{"type":"QUEST_GUIDE_NONE","param":[]},"exclusiveNpcList":[],"sharedNpcList":[],"exclusivePlaceList":[],"descTextMapHash":1698707934,"stepDescTextMapHash":2695381091,"guideTipsTextMapHash":1475863340},{"subId":2230605,"mainId":22306,"order":18,"finishParent":true,"isRewind":true,"trialAvatarList":[],"acceptCondComb":"LOGIC_AND","acceptCond":[{"type":"QUEST_COND_DAILY_TASK_START","param":[25901,0,0,0,0]},{"type":"QUEST_COND_STATE_EQUAL","param":[2230604,3,0,0,0]}],"finishCondComb":"LOGIC_OR","finishCond":[{"type":"QUEST_CONTENT_COMPLETE_TALK","param":[2230606,0]},{"type":"QUEST_CONTENT_COMPLETE_TALK","param":[2230609,0]}],"failCond":[],"beginExec":[],"finishExec":[{"type":"QUEST_EXEC_NOTIFY_DAILY_TASK","param":["25901"]}],"failExec":[],"guide":{"type":"QUEST_GUIDE_NPC","param":["2013"],"guideScene":3,"guideStyle":"QUEST_GUIDE_STYLE_FINISH","guideLayer":"QUEST_GUIDE_LAYER_SCENE"},"exclusiveNpcList":[2033,2013],"sharedNpcList":[],"exclusivePlaceList":[],"descTextMapHash":255208278,"stepDescTextMapHash":2223977779,"guideTipsTextMapHash":203794124},{"subId":2230611,"mainId":22306,"order":5,"showType":"QUEST_HIDDEN","isRewind":true,"trialAvatarList":[],"acceptCondComb":"LOGIC_AND","acceptCond":[{"type":"QUEST_COND_DAILY_TASK_START","param":[25901,0,0,0,0]},{"type":"QUEST_COND_STATE_EQUAL","param":[2230601,3,0,0,0]},{"type":"QUEST_COND_QUEST_VAR_EQUAL","param":[0,1,0,0,0]}],"finishCond":[{"type":"QUEST_CONTENT_LUA_NOTIFY","paramString":"13310444201","param":[0,0],"count":1}],"failCond":[],"beginExec":[{"type":"QUEST_EXEC_REFRESH_GROUP_SUITE","param":["3","133104442,2"]},{"type":"QUEST_EXEC_REFRESH_GROUP_SUITE","param":["3","133104446,2"]}],"finishExec":[{"type":"QUEST_EXEC_ADD_QUEST_PROGRESS","param":["223060401","1"]},{"type":"QUEST_EXEC_REFRESH_GROUP_SUITE","param":["3","133104446,1"]},{"type":"QUEST_EXEC_REFRESH_GROUP_SUITE","param":["3","133104442,1"]}],"failExec":[],"guide":{"type":"QUEST_GUIDE_NONE","param":[]},"exclusiveNpcList":[],"sharedNpcList":[],"exclusivePlaceList":[],"descTextMapHash":3936440878,"stepDescTextMapHash":243903507,"guideTipsTextMapHash":3578444636,"gainItems":[{"itemId":100395,"count":1}]},{"subId":2230612,"mainId":22306,"order":6,"showType":"QUEST_HIDDEN","isRewind":true,"trialAvatarList":[],"acceptCondComb":"LOGIC_AND","acceptCond":[{"type":"QUEST_COND_DAILY_TASK_START","param":[25901,0,0,0,0]},{"type":"QUEST_COND_STATE_EQUAL","param":[2230601,3,0,0,0]},{"type":"QUEST_COND_QUEST_VAR_EQUAL","param":[0,2,0,0,0]}],"finishCond":[{"type":"QUEST_CONTENT_LUA_NOTIFY","paramString":"13310444301","param":[0,0],"count":1}],"failCond":[],"beginExec":[{"type":"QUEST_EXEC_REFRESH_GROUP_SUITE","param":["3","133104443,2"]},{"type":"QUEST_EXEC_REFRESH_GROUP_SUITE","param":["3","133104447,2"]}],"finishExec":[{"type":"QUEST_EXEC_ADD_QUEST_PROGRESS","param":["223060401","1"]},{"type":"QUEST_EXEC_REFRESH_GROUP_SUITE","param":["3","133104443,1"]},{"type":"QUEST_EXEC_REFRESH_GROUP_SUITE","param":["3","133104447,1"]}],"failExec":[],"guide":{"type":"QUEST_GUIDE_NONE","param":[]},"exclusiveNpcList":[],"sharedNpcList":[],"exclusivePlaceList":[],"descTextMapHash":2990519406,"stepDescTextMapHash":2797447515,"guideTipsTextMapHash":3911462412,"gainItems":[{"itemId":100396,"count":1}]},{"subId":2230613,"mainId":22306,"order":7,"showType":"QUEST_HIDDEN","isRewind":true,"trialAvatarList":[],"acceptCondComb":"LOGIC_AND","acceptCond":[{"type":"QUEST_COND_DAILY_TASK_START","param":[25901,0,0,0,0]},{"type":"QUEST_COND_STATE_EQUAL","param":[2230601,3,0,0,0]},{"type":"QUEST_COND_QUEST_VAR_EQUAL","param":[0,3,0,0,0]}],"finishCond":[{"type":"QUEST_CONTENT_LUA_NOTIFY","paramString":"13310444401","param":[0,0],"count":1}],"failCond":[],"beginExec":[{"type":"QUEST_EXEC_REFRESH_GROUP_SUITE","param":["3","133104444,2"]},{"type":"QUEST_EXEC_REFRESH_GROUP_SUITE","param":["3","133104448,3"]}],"finishExec":[{"type":"QUEST_EXEC_ADD_QUEST_PROGRESS","param":["223060401","1"]},{"type":"QUEST_EXEC_REFRESH_GROUP_SUITE","param":["3","133104444,1"]},{"type":"QUEST_EXEC_REFRESH_GROUP_SUITE","param":["3","133104448,1"]}],"failExec":[],"guide":{"type":"QUEST_GUIDE_NONE","param":[]},"exclusiveNpcList":[],"sharedNpcList":[],"exclusivePlaceList":[],"descTextMapHash":2381830790,"stepDescTextMapHash":3537609499,"guideTipsTextMapHash":189094892,"gainItems":[{"itemId":100395,"count":1}]},{"subId":2230621,"mainId":22306,"order":11,"isRewind":true,"trialAvatarList":[],"acceptCondComb":"LOGIC_AND","acceptCond":[{"type":"QUEST_COND_DAILY_TASK_START","param":[25901,0,0,0,0]},{"type":"QUEST_COND_STATE_EQUAL","param":[2230602,3,0,0,0]},{"type":"QUEST_COND_QUEST_VAR_EQUAL","param":[0,1,0,0,0]}],"finishCondComb":"LOGIC_OR","finishCond":[{"type":"QUEST_CONTENT_LUA_NOTIFY","paramString":"13310444202","param":[0,0],"count":1},{"type":"QUEST_CONTENT_COMPLETE_TALK","param":[2230603,0]}],"failCond":[],"beginExec":[],"finishExec":[],"failExec":[],"guide":{"type":"QUEST_GUIDE_NPC","param":["2013"],"guideScene":3,"guideStyle":"QUEST_GUIDE_STYLE_TARGET","guideLayer":"QUEST_GUIDE_LAYER_SCENE"},"exclusiveNpcList":[2033,2013],"sharedNpcList":[],"exclusivePlaceList":[],"descTextMapHash":773394206,"stepDescTextMapHash":2282503363,"guideTipsTextMapHash":3240226276},{"subId":2230622,"mainId":22306,"order":12,"isRewind":true,"trialAvatarList":[],"acceptCondComb":"LOGIC_AND","acceptCond":[{"type":"QUEST_COND_DAILY_TASK_START","param":[25901,0,0,0,0]},{"type":"QUEST_COND_STATE_EQUAL","param":[2230602,3,0,0,0]},{"type":"QUEST_COND_QUEST_VAR_EQUAL","param":[0,2,0,0,0]}],"finishCondComb":"LOGIC_OR","finishCond":[{"type":"QUEST_CONTENT_LUA_NOTIFY","paramString":"13310444302","param":[0,0],"count":1},{"type":"QUEST_CONTENT_COMPLETE_TALK","param":[2230603,0]}],"failCond":[],"beginExec":[],"finishExec":[],"failExec":[],"guide":{"type":"QUEST_GUIDE_NPC","param":["2013"],"guideScene":3,"guideStyle":"QUEST_GUIDE_STYLE_TARGET","guideLayer":"QUEST_GUIDE_LAYER_SCENE"},"exclusiveNpcList":[2033,2013],"sharedNpcList":[],"exclusivePlaceList":[],"descTextMapHash":1800941278,"stepDescTextMapHash":3302984339,"guideTipsTextMapHash":836012212},{"subId":2230623,"mainId":22306,"order":13,"isRewind":true,"trialAvatarList":[],"acceptCondComb":"LOGIC_AND","acceptCond":[{"type":"QUEST_COND_DAILY_TASK_START","param":[25901,0,0,0,0]},{"type":"QUEST_COND_STATE_EQUAL","param":[2230602,3,0,0,0]},{"type":"QUEST_COND_QUEST_VAR_EQUAL","param":[0,3,0,0,0]}],"finishCondComb":"LOGIC_OR","finishCond":[{"type":"QUEST_CONTENT_LUA_NOTIFY","paramString":"13310444402","param":[0,0],"count":1},{"type":"QUEST_CONTENT_COMPLETE_TALK","param":[2230603,0]}],"failCond":[],"beginExec":[],"finishExec":[],"failExec":[],"guide":{"type":"QUEST_GUIDE_NPC","param":["2013"],"guideScene":3,"guideStyle":"QUEST_GUIDE_STYLE_TARGET","guideLayer":"QUEST_GUIDE_LAYER_SCENE"},"exclusiveNpcList":[2033,2013],"sharedNpcList":[],"exclusivePlaceList":[],"descTextMapHash":4177250606,"stepDescTextMapHash":1233645315,"guideTipsTextMapHash":3013078708},{"subId":2230631,"mainId":22306,"order":14,"isRewind":true,"trialAvatarList":[],"acceptCondComb":"LOGIC_AND","acceptCond":[{"type":"QUEST_COND_DAILY_TASK_START","param":[25901,0,0,0,0]},{"type":"QUEST_COND_STATE_EQUAL","param":[2230621,3,0,0,0]}],"finishCond":[{"type":"QUEST_CONTENT_LUA_NOTIFY","paramString":"13310444201","param":[0,0],"count":1}],"failCond":[],"beginExec":[],"finishExec":[],"failExec":[],"guide":{"type":"QUEST_GUIDE_LOCATION","param":["Event_25901C","60"],"guideScene":3,"guideStyle":"QUEST_GUIDE_STYLE_TARGET","guideLayer":"QUEST_GUIDE_LAYER_SCENE"},"exclusiveNpcList":[2033,2013],"sharedNpcList":[],"exclusivePlaceList":[],"descTextMapHash":4079320990,"stepDescTextMapHash":3044263035,"guideTipsTextMapHash":3983544468},{"subId":2230632,"mainId":22306,"order":15,"isRewind":true,"trialAvatarList":[],"acceptCondComb":"LOGIC_AND","acceptCond":[{"type":"QUEST_COND_DAILY_TASK_START","param":[25901,0,0,0,0]},{"type":"QUEST_COND_STATE_EQUAL","param":[2230622,3,0,0,0]}],"finishCond":[{"type":"QUEST_CONTENT_LUA_NOTIFY","paramString":"13310444301","param":[0,0],"count":1}],"failCond":[],"beginExec":[],"finishExec":[],"failExec":[],"guide":{"type":"QUEST_GUIDE_LOCATION","param":["Event_25901C","60"],"guideScene":3,"guideStyle":"QUEST_GUIDE_STYLE_TARGET","guideLayer":"QUEST_GUIDE_LAYER_SCENE"},"exclusiveNpcList":[2033,2013],"sharedNpcList":[],"exclusivePlaceList":[],"descTextMapHash":448552990,"stepDescTextMapHash":432321299,"guideTipsTextMapHash":3435858660},{"subId":2230633,"mainId":22306,"order":16,"isRewind":true,"trialAvatarList":[],"acceptCondComb":"LOGIC_AND","acceptCond":[{"type":"QUEST_COND_DAILY_TASK_START","param":[25901,0,0,0,0]},{"type":"QUEST_COND_STATE_EQUAL","param":[2230623,3,0,0,0]}],"finishCond":[{"type":"QUEST_CONTENT_LUA_NOTIFY","paramString":"13310444401","param":[0,0],"count":1}],"failCond":[],"beginExec":[],"finishExec":[],"failExec":[],"guide":{"type":"QUEST_GUIDE_LOCATION","param":["Event_25901C","60"],"guideScene":3,"guideStyle":"QUEST_GUIDE_STYLE_TARGET","guideLayer":"QUEST_GUIDE_LAYER_SCENE"},"exclusiveNpcList":[2033,2013],"sharedNpcList":[],"exclusivePlaceList":[],"descTextMapHash":2294579038,"stepDescTextMapHash":3630172771,"guideTipsTextMapHash":3451574756},{"subId":2230641,"mainId":22306,"order":8,"showType":"QUEST_HIDDEN","isRewind":true,"trialAvatarList":[],"acceptCondComb":"LOGIC_AND","acceptCond":[{"type":"QUEST_COND_DAILY_TASK_START","param":[25901,0,0,0,0]},{"type":"QUEST_COND_STATE_EQUAL","param":[2230601,3,0,0,0]},{"type":"QUEST_COND_QUEST_VAR_EQUAL","param":[0,1,0,0,0]}],"finishCond":[{"type":"QUEST_CONTENT_COMPLETE_TALK","param":[2230602,0]}],"failCond":[],"beginExec":[],"finishExec":[],"failExec":[],"guide":{"type":"QUEST_GUIDE_NONE","param":[]},"exclusiveNpcList":[],"sharedNpcList":[],"exclusivePlaceList":[],"descTextMapHash":2105502214,"stepDescTextMapHash":1092853811,"guideTipsTextMapHash":3812067604,"gainItems":[{"itemId":100416,"count":1}]},{"subId":2230642,"mainId":22306,"order":9,"showType":"QUEST_HIDDEN","isRewind":true,"trialAvatarList":[],"acceptCondComb":"LOGIC_AND","acceptCond":[{"type":"QUEST_COND_DAILY_TASK_START","param":[25901,0,0,0,0]},{"type":"QUEST_COND_STATE_EQUAL","param":[2230601,3,0,0,0]},{"type":"QUEST_COND_QUEST_VAR_EQUAL","param":[0,2,0,0,0]}],"finishCond":[{"type":"QUEST_CONTENT_COMPLETE_TALK","param":[2230602,0]}],"failCond":[],"beginExec":[],"finishExec":[],"failExec":[],"guide":{"type":"QUEST_GUIDE_NONE","param":[]},"exclusiveNpcList":[],"sharedNpcList":[],"exclusivePlaceList":[],"descTextMapHash":4098376950,"stepDescTextMapHash":3110326027,"guideTipsTextMapHash":3693276828,"gainItems":[{"itemId":100415,"count":1}]},{"subId":2230643,"mainId":22306,"order":10,"showType":"QUEST_HIDDEN","isRewind":true,"trialAvatarList":[],"acceptCondComb":"LOGIC_AND","acceptCond":[{"type":"QUEST_COND_DAILY_TASK_START","param":[25901,0,0,0,0]},{"type":"QUEST_COND_STATE_EQUAL","param":[2230601,3,0,0,0]},{"type":"QUEST_COND_QUEST_VAR_EQUAL","param":[0,3,0,0,0]}],"finishCond":[{"type":"QUEST_CONTENT_COMPLETE_TALK","param":[2230602,0]}],"failCond":[],"beginExec":[],"finishExec":[],"failExec":[],"guide":{"type":"QUEST_GUIDE_NONE","param":[]},"exclusiveNpcList":[],"sharedNpcList":[],"exclusivePlaceList":[],"descTextMapHash":2328985814,"stepDescTextMapHash":2398650611,"guideTipsTextMapHash":1840664580,"gainItems":[{"itemId":100414,"count":1}]},{"subId":2230651,"mainId":22306,"order":17,"showType":"QUEST_HIDDEN","trialAvatarList":[],"acceptCondComb":"LOGIC_AND","acceptCond":[{"type":"QUEST_COND_DAILY_TASK_START","param":[25901,0,0,0,0]},{"type":"QUEST_COND_STATE_EQUAL","param":[2230602,3,0,0,0]}],"finishCondComb":"LOGIC_OR","finishCond":[{"type":"QUEST_CONTENT_LUA_NOTIFY","paramString":"13310444402","param":[0,0],"count":1}],"failCond":[],"beginExec":[],"finishExec":[],"failExec":[],"guide":{"type":"QUEST_GUIDE_NONE","param":[]},"exclusiveNpcList":[],"sharedNpcList":[],"exclusivePlaceList":[],"descTextMapHash":4258341022,"stepDescTextMapHash":509148147,"guideTipsTextMapHash":2541421412}],"talks":[{"id":2230601,"beginWay":"TALK_BEGIN_MANUAL","beginCond":[{"type":"QUEST_COND_STATE_EQUAL","params":["2230601","2"]}],"activeMode":"PLAY_MODE_ALL","priority":5,"initDialog":223060101,"npcIds":[2033],"performCfg":"","prePerformCfg":"","questId":22306,"assetIndex":636564384971},{"id":2230602,"beginWay":"TALK_BEGIN_MANUAL","beginCondComb":"LOGIC_AND","beginCond":[{"type":"QUEST_COND_STATE_EQUAL","params":["2230602","2"]},{"type":"QUEST_COND_STATE_NOT_EQUAL","params":["2230604","3"]}],"activeMode":"PLAY_MODE_ALL","nextTalks":[2230608],"priority":5,"initDialog":223060201,"npcIds":[2013],"performCfg":"","prePerformCfg":"","questId":22306,"assetIndex":1048310403754},{"id":2230603,"beginCond":[{"type":"QUEST_COND_PACK_HAVE_ITEM","params":["202","100"]}],"activeMode":"PLAY_MODE_ALL","priority":5,"initDialog":223060301,"npcIds":[2013],"performCfg":"","prePerformCfg":"","questId":22306,"assetIndex":585536702581},{"id":2230604,"activeMode":"PLAY_MODE_ALL","priority":5,"initDialog":223060401,"npcIds":[2013],"performCfg":"","prePerformCfg":"","questId":22306,"assetIndex":250402938054},{"id":2230605,"beginWay":"TALK_BEGIN_MANUAL","beginCondComb":"LOGIC_AND","beginCond":[{"type":"QUEST_COND_DAILY_TASK_IN_PROGRESS","params":["25901"]},{"type":"QUEST_COND_STATE_EQUAL","params":["2230601","3"]}],"activeMode":"PLAY_MODE_ALL","priority":5,"initDialog":223060501,"npcIds":[2033],"performCfg":"","prePerformCfg":"","questId":22306,"assetIndex":549864973030},{"id":2230606,"beginWay":"TALK_BEGIN_MANUAL","beginCond":[{"type":"QUEST_COND_STATE_EQUAL","params":["2230605","2"]},{"type":"QUEST_COND_PACK_HAVE_ITEM","params":["100395","1"]}],"activeMode":"PLAY_MODE_ALL","priority":5,"initDialog":223060601,"npcIds":[2013],"performCfg":"","prePerformCfg":"","questId":22306,"assetIndex":833448226520},{"id":2230607,"beginWay":"TALK_BEGIN_MANUAL","beginCondComb":"LOGIC_AND","beginCond":[{"type":"QUEST_COND_STATE_EQUAL","params":["2230604","2"]},{"type":"QUEST_COND_STATE_NOT_EQUAL","params":["2230603","3"]},{"type":"QUEST_COND_STATE_NOT_EQUAL","params":["2230602","2"]}],"activeMode":"PLAY_MODE_ALL","nextTalks":[2230603,2230604],"priority":5,"initDialog":223060701,"npcIds":[2013],"performCfg":"","prePerformCfg":"","questId":22306,"assetIndex":38715777044},{"id":2230608,"activeMode":"PLAY_MODE_ALL","nextTalks":[2230603,2230604],"priority":5,"initDialog":223060801,"npcIds":[2013],"performCfg":"","prePerformCfg":"","questId":22306,"assetIndex":775074294911},{"id":2230609,"beginWay":"TALK_BEGIN_MANUAL","beginCond":[{"type":"QUEST_COND_STATE_EQUAL","params":["2230605","2"]},{"type":"QUEST_COND_PACK_HAVE_ITEM","params":["100396","1"]}],"activeMode":"PLAY_MODE_ALL","priority":5,"initDialog":223060901,"npcIds":[2013],"performCfg":"","prePerformCfg":"","questId":22306,"assetIndex":830819527543}]}