{"id":355,"collectionId":1001,"series":1001,"chapterId":1001,"luaPath":"Actor/Quest/AQ355","suggestTrackMainQuestList":[354],"rewardIdList":[100355],"activeMode":"PLAY_MODE_SINGLE","titleTextMapHash":1760868089,"descTextMapHash":70357895,"subQuests":[{"subId":35501,"mainId":355,"order":1,"trialAvatarList":[],"acceptCond":[{"type":"QUEST_COND_STATE_EQUAL","param":[35311,3,0,0,0]}],"finishCond":[{"type":"QUEST_CONTENT_FINISH_PLOT","param":[36101,0]}],"failCond":[],"beginExec":[],"finishExec":[],"failExec":[],"guide":{"type":"QUEST_GUIDE_LOCATION","param":["Q301WendyPlay"],"guideScene":3,"autoGuide":"QUEST_GUIDE_AUTO_ENABLE"},"showGuide":"QUEST_GUIDE_ITEM_DISABLE","exclusiveNpcList":[],"sharedNpcList":[],"exclusivePlaceList":[],"descTextMapHash":1480972647,"stepDescTextMapHash":2424771631,"guideTipsTextMapHash":2634426023},{"subId":35502,"mainId":355,"order":2,"trialAvatarList":[],"acceptCondComb":"LOGIC_AND","acceptCond":[{"type":"QUEST_COND_STATE_EQUAL","param":[35501,3,0,0,0]},{"type":"QUEST_COND_STATE_EQUAL","param":[36101,3,0,0,0]}],"finishCond":[{"type":"QUEST_CONTENT_TRIGGER_FIRE","param":[1022,0]}],"failCond":[],"beginExec":[],"finishExec":[],"failExec":[],"guide":{"type":"QUEST_GUIDE_LOCATION","param":["Q355Stone"],"guideScene":3,"autoGuide":"QUEST_GUIDE_AUTO_DISABLE"},"showGuide":"QUEST_GUIDE_ITEM_DISABLE","exclusiveNpcList":[],"sharedNpcList":[],"exclusivePlaceList":[],"descTextMapHash":3003853399,"stepDescTextMapHash":3728775671,"guideTipsTextMapHash":1913042687},{"subId":35503,"mainId":355,"order":3,"isRewind":true,"trialAvatarList":[],"acceptCond":[{"type":"QUEST_COND_STATE_EQUAL","param":[35502,3,0,0,0]}],"finishCond":[{"type":"QUEST_CONTENT_COMPLETE_TALK","param":[35507,0]}],"failCond":[],"beginExec":[],"finishExec":[],"failExec":[],"guide":{"type":"QUEST_GUIDE_NPC","param":["1005"],"guideScene":3,"guideStyle":"QUEST_GUIDE_STYLE_TARGET","guideLayer":"QUEST_GUIDE_LAYER_SCENE"},"exclusiveNpcList":[],"sharedNpcList":[],"exclusivePlaceList":[],"descTextMapHash":2752259839,"stepDescTextMapHash":3221389439,"guideTipsTextMapHash":4165242639},{"subId":35504,"mainId":355,"order":4,"isRewind":true,"trialAvatarList":[],"acceptCond":[{"type":"QUEST_COND_STATE_EQUAL","param":[35503,3,0,0,0]}],"finishCond":[{"type":"QUEST_CONTENT_OBTAIN_ITEM","param":[100135,0]}],"failCond":[],"beginExec":[],"finishExec":[],"failExec":[],"guide":{"type":"QUEST_GUIDE_LOCATION","param":["Q355Stone2"],"guideScene":3,"guideStyle":"QUEST_GUIDE_STYLE_TARGET","guideLayer":"QUEST_GUIDE_LAYER_UI"},"exclusiveNpcList":[],"sharedNpcList":[],"exclusivePlaceList":[],"descTextMapHash":2764279735,"stepDescTextMapHash":970719231,"guideTipsTextMapHash":3578343911},{"subId":35505,"mainId":355,"order":5,"finishParent":true,"isRewind":true,"trialAvatarList":[],"acceptCond":[{"type":"QUEST_COND_STATE_EQUAL","param":[35504,3,0,0,0]}],"finishCond":[{"type":"QUEST_CONTENT_COMPLETE_TALK","param":[35506,0]}],"failCond":[],"beginExec":[],"finishExec":[],"failExec":[],"guide":{"type":"QUEST_GUIDE_NPC","param":["1005"],"guideScene":3,"guideStyle":"QUEST_GUIDE_STYLE_TARGET","guideLayer":"QUEST_GUIDE_LAYER_SCENE"},"exclusiveNpcList":[],"sharedNpcList":[],"exclusivePlaceList":[],"descTextMapHash":4123189991,"stepDescTextMapHash":562150719,"guideTipsTextMapHash":3108721119}],"talks":[{"id":35506,"beginWay":"TALK_BEGIN_MANUAL","beginCond":[{"type":"QUEST_COND_STATE_EQUAL","params":["35505","2"]}],"priority":5,"initDialog":3550601,"npcIds":[1005],"performCfg":"QuestDialogue/AQ/Mengde1_355/Q35506","prePerformCfg":"","questId":355,"assetIndex":110577717920},{"id":35507,"beginWay":"TALK_BEGIN_MANUAL","beginCond":[{"type":"QUEST_COND_STATE_EQUAL","params":["35503","2"]}],"heroTalk":"TALK_HERO_MAIN","priority":5,"initDialog":3550701,"npcIds":[1005],"performCfg":"QuestDialogue/AQ/Mengde1_355/Q35507","prePerformCfg":"","questId":355,"assetIndex":1052057927782}],"preloadLuaList":[645902683150],"freeStyleDic":{"1005":[1200]}}