{"id":72668,"taskType":"WQ","luaPath":"Actor/Quest/WQ72668","showType":"QUEST_HIDDEN","suggestTrackMainQuestList":[],"rewardIdList":[],"activeMode":"PLAY_MODE_SINGLE","titleTextMapHash":106875695,"descTextMapHash":601504078,"subQuests":[{"subId":7266801,"mainId":72668,"order":1,"showType":"QUEST_HIDDEN","isRewind":true,"trialAvatarList":[],"acceptCondComb":"LOGIC_AND","acceptCond":[{"type":"QUEST_COND_STATE_EQUAL","param":[7266304,3,0,0,0]},{"type":"QUEST_COND_ACTIVITY_COND","param":[5041010,1,0,0,0]}],"finishCond":[{"type":"QUEST_CONTENT_LUA_NOTIFY","paramString":"7266801","param":[0,0],"count":1}],"failCond":[],"beginExec":[],"finishExec":[],"failExec":[],"guide":{"type":"QUEST_GUIDE_NONE","param":[]},"exclusiveNpcList":[],"sharedNpcList":[],"exclusivePlaceList":[],"descTextMapHash":2751061716,"stepDescTextMapHash":3092010061,"guideTipsTextMapHash":1877926870},{"subId":7266802,"mainId":72668,"order":2,"showType":"QUEST_HIDDEN","finishParent":true,"trialAvatarList":[],"acceptCond":[{"type":"QUEST_COND_STATE_EQUAL","param":[7266801,3,0,0,0]}],"finishCond":[{"type":"QUEST_CONTENT_COMPLETE_TALK","param":[7266801,0]}],"failCond":[],"beginExec":[],"finishExec":[],"failExec":[],"guide":{"type":"QUEST_GUIDE_NONE","param":[]},"exclusiveNpcList":[],"sharedNpcList":[],"exclusivePlaceList":[],"descTextMapHash":3871313788,"stepDescTextMapHash":3190938949,"guideTipsTextMapHash":1338267046}],"talks":[{"id":7266801,"beginWay":"TALK_BEGIN_MANUAL","beginCond":[{"type":"QUEST_COND_STATE_EQUAL","params":["7266802","2"]}],"heroTalk":"TALK_HERO_MAIN","priority":5,"initDialog":726680101,"npcIds":[1005],"performCfg":"","prePerformCfg":"","questId":72668,"assetIndex":452163605741}],"preloadLuaList":[645902683150]}